Oasis/__init__.py
Oasis/constraint.py
Oasis/gradient.py
Oasis/history.py
Oasis/objective.py
Oasis/optimization.py
Oasis/optimizer.py
Oasis/parameter.py
Oasis/variable.py
Oasis/harmonysearch/__init__.py
Oasis/harmonysearch/hs.py
Oasis/harmonysearch/hsapi.py
Oasis_Optimization-1.0.3.dist-info/LICENSE
Oasis_Optimization-1.0.3.dist-info/METADATA
Oasis_Optimization-1.0.3.dist-info/WHEEL
Oasis_Optimization-1.0.3.dist-info/top_level.txt
Oasis_Optimization-1.0.3.dist-info/RECORD
