Metadata-Version: 2.1
Name: Oasis-Optimization
Version: 1.0.3
Summary: Oasis is a Harmony search optimization algorithm.
Author-email: Mostafa Farrag <moah.farag@gmail.come>
License: GNU General Public License v3
Project-URL: homepage, https://github.com/MAfarrag/Oasis
Keywords: Optimization,Harmony Search
Classifier: Development Status :: 5 - Production/Stable
Classifier: Environment :: Console
Classifier: Intended Audience :: Developers
Classifier: Natural Language :: English
Classifier: Programming Language :: Python
Classifier: Programming Language :: Python :: 3.6
Classifier: Programming Language :: Python :: 3.7
Classifier: Programming Language :: Python :: 3.8
Classifier: Programming Language :: Python :: 3.9
Classifier: Programming Language :: Python :: 3.10
Classifier: Topic :: Software Development
Requires-Python: >=3.0
License-File: LICENSE
Requires-Dist: numpy>=2.0.0
Provides-Extra: test
Requires-Dist: pytest>=8.2.2; extra == "test"
Requires-Dist: pytest-cov>=6.0.0; extra == "test"
Requires-Dist: nbval>=0.11.0; extra == "test"
Requires-Dist: coverage; extra == "test"
